kort/__init__.py
kort/config.py
kort/data/__init__.py
kort/data/evaluate.py
kort/data/generate.py
kort/data/lang_code.py
kort/data/prompts.py
kort/evaluators/__init__.py
kort/evaluators/base_evaluator.py
kort/evaluators/from_batch.py
kort/evaluators/from_model.py
kort/evaluators/human/__init__.py
kort/evaluators/human/human.py
kort/leaderboards/__init__.py
kort/leaderboards/base_leaderboard.py
kort/leaderboards/leaderboard_text.py
kort/leaderboards/leaderboard_web.py
kort/models/__init__.py
kort/models/base_model.py
kort/models/batch_model.py
kort/models/transformer_model.py
kort/models/anthropic/__init__.py
kort/models/anthropic/claude.py
kort/models/anthropic/claude_batch.py
kort/models/custom/__init__.py
kort/models/custom/gemago.py
kort/models/custom/gugugo.py
kort/models/google/__init__.py
kort/models/google/gemini.py
kort/models/openai/__init__.py
kort/models/openai/gpt.py
kort/models/openai/gpt_batch.py
kort/scripts/__init__.py
kort/scripts/eval_batch.py
kort/scripts/evaluate.py
kort/scripts/generate.py
kort/scripts/leaderboard.py
kort/translators/__init__.py
kort/translators/base_translator.py
kort/translators/from_model.py
kort/translators/deepl/__init__.py
kort/translators/deepl/deepl_api.py
kort/translators/deepl/deepl_free.py
kort/translators/google/__init__.py
kort/translators/google/google_free.py
kort/translators/kakao/__init__.py
kort/translators/kakao/kakao_free.py
kort/translators/naver/__init__.py
kort/translators/naver/papago_free.py
kort/utils/__init__.py
kort/utils/exceptions.py
kort/utils/import_utils.py
kort/utils/retry.py
kort_cli-1.0.2.dist-info/licenses/LICENSE
kort_cli-1.0.2.dist-info/METADATA
kort_cli-1.0.2.dist-info/WHEEL
kort_cli-1.0.2.dist-info/top_level.txt
kort_cli-1.0.2.dist-info/RECORD
