Metadata-Version: 2.4
Name: kort-cli
Version: 1.0.2
Summary: 한국어 번역 능력 벤치마크, LLM-as-a-judge
Author-email: World <world@worldsw.dev>
License-Expression: Apache-2.0
Project-URL: Homepage, https://github.com/deveworld/KorT
Project-URL: Issues, https://github.com/deveworld/KorT/issues
Requires-Python: >=3.11
License-File: LICENSE
Requires-Dist: deepl>=1.21.1
Requires-Dist: openai>=1.70.0
Requires-Dist: google-genai>=1.10.0
Requires-Dist: anthropic>=0.49.0
Requires-Dist: tqdm>=4.65.0
Requires-Dist: pydantic>=2.10.0
Requires-Dist: gradio>=5.25.0
Requires-Dist: pandas>=2.0.0
Requires-Dist: googletrans>=4.0.0
Provides-Extra: local
Requires-Dist: torch>=2.0.0; extra == "local"
Requires-Dist: transformers>=4.30.0; extra == "local"
Provides-Extra: all
Requires-Dist: kort-cli[local]; extra == "all"
Dynamic: license-file
